azure/__init__.py
azure/cli/__init__.py
azure/cli/command_modules/__init__.py
azure/cli/command_modules/cognitiveservices/__init__.py
azure/cli/command_modules/cognitiveservices/_client_factory.py
azure/cli/command_modules/cognitiveservices/_help.py
azure/cli/command_modules/cognitiveservices/_params.py
azure/cli/command_modules/cognitiveservices/commands.py
azure/cli/command_modules/cognitiveservices/custom.py
azure_cli_cognitiveservices-0.2.6.dist-info/METADATA
azure_cli_cognitiveservices-0.2.6.dist-info/WHEEL
azure_cli_cognitiveservices-0.2.6.dist-info/top_level.txt
azure_cli_cognitiveservices-0.2.6.dist-info/RECORD
